topsis/__init__.py
topsis/cli.py
topsis_tarun-0.1.0.dist-info/METADATA
topsis_tarun-0.1.0.dist-info/WHEEL
topsis_tarun-0.1.0.dist-info/entry_points.txt
topsis_tarun-0.1.0.dist-info/top_level.txt
topsis_tarun-0.1.0.dist-info/RECORD
