Metadata-Version: 2.4
Name: topsis-tarun
Version: 0.1.0
Summary: Command-line implementation of TOPSIS (MCDA technique)
Author-email: Tarun Krishna Shastri <tshastri_be23@thapar.edu>
License: MIT
Requires-Python: >=3.8
Requires-Dist: pandas
Requires-Dist: numpy
